energyml/__init__.py
energyml/utils/__init__.py
energyml/utils/constants.py
energyml/utils/data/__init__.py
energyml/utils/data/datasets_io.py
energyml/utils/data/helper.py
energyml/utils/data/mesh.py
energyml/utils/data/model.py
energyml/utils/epc.py
energyml/utils/epc_stream.py
energyml/utils/exception.py
energyml/utils/introspection.py
energyml/utils/manager.py
energyml/utils/rc/PropertyKindDictionary_v2.3.json
energyml/utils/rc/PropertyKindDictionary_v2.3.xml
energyml/utils/rc/__init__.py
energyml/utils/serialization.py
energyml/utils/uri.py
energyml/utils/validation.py
energyml/utils/workspace.py
energyml/utils/xml.py
energyml_utils-1.9.2.dist-info/LICENSE
energyml_utils-1.9.2.dist-info/METADATA
energyml_utils-1.9.2.dist-info/WHEEL
energyml_utils-1.9.2.dist-info/entry_points.txt
energyml_utils-1.9.2.dist-info/RECORD
