Metadata-Version: 2.1
Name: energyml-utils
Version: 1.9.2
Summary: Energyml helper
Home-page: http://www.geosiris.com
License: Apache-2.0
Keywords: energyml,resqml,witsml,prodml
Author: Valentin Gauthier
Author-email: valentin.gauthier@geosiris.com
Maintainer: Valentin Gauthier
Maintainer-email: valentin.gauthier@geosiris.com
Requires-Python: >=3.9,<4.0
Classifier: Development Status :: 4 - Beta
Classifier: Environment :: Web Environment
Classifier: Intended Audience :: Developers
Classifier: Intended Audience :: Information Technology
Classifier: License :: OSI Approved :: Apache Software License
Classifier: Operating System :: OS Independent
Classifier: Programming Language :: Python
Classifier: Programming Language :: Python :: 3
Classifier: Programming Language :: Python :: 3.9
Classifier: Programming Language :: Python :: 3.10
Classifier: Programming Language :: Python :: 3.11
Classifier: Topic :: Internet
Classifier: Topic :: Software Development
Classifier: Topic :: Software Development :: Libraries
Classifier: Topic :: Software Development :: Libraries :: Application Frameworks
Classifier: Topic :: Software Development :: Libraries :: Python Modules
Provides-Extra: hdf5
Provides-Extra: parquet
Requires-Dist: energyml-opc (>=1.12.0,<2.0.0)
Requires-Dist: flake8 (>=7.3.0,<8.0.0)
Requires-Dist: h5py (>=3.7.0,<4.0.0) ; extra == "hdf5"
Requires-Dist: numpy (>=1.16.6,<2.0.0) ; extra == "parquet"
Requires-Dist: pyarrow (>=14.0.1,<15.0.0) ; extra == "parquet"
Requires-Dist: xsdata[cli,lxml] (>=24.0,<25.0)
Project-URL: Repository, https://github.com/geosiris-technologies/energyml-python
